napari_label_focus/__init__.py
napari_label_focus/_context.py
napari_label_focus/_events.py
napari_label_focus/_featurizers.py
napari_label_focus/_version.py
napari_label_focus/_widget.py
napari_label_focus/napari.yaml
napari_label_focus-0.2.0.dist-info/licenses/LICENSE
napari_label_focus-0.2.0.dist-info/METADATA
napari_label_focus-0.2.0.dist-info/WHEEL
napari_label_focus-0.2.0.dist-info/entry_points.txt
napari_label_focus-0.2.0.dist-info/top_level.txt
napari_label_focus-0.2.0.dist-info/RECORD
