Metadata-Version: 2.4
Name: napari-label-focus
Version: 0.2.0
Summary: A configurable features table widget for Napari.
Author-email: Mallory Wittwer <mallory.wittwer@epfl.ch>
License: Copyright (c) 2024, EPFL
Project-URL: homepage, https://github.com/EPFL-Center-for-Imaging/napari-label-focus
Project-URL: repository, https://github.com/EPFL-Center-for-Imaging/napari-label-focus
Classifier: Development Status :: 2 - Pre-Alpha
Classifier: License :: OSI Approved :: BSD License
Classifier: Programming Language :: Python :: 3
Classifier: Programming Language :: Python :: 3.9
Classifier: Programming Language :: Python :: 3.10
Classifier: Programming Language :: Python :: 3.11
Classifier: Programming Language :: Python :: 3.12
Classifier: Programming Language :: Python :: 3.13
Classifier: Topic :: Scientific/Engineering :: Image Processing
Requires-Python: >=3.9
License-File: LICENSE
Requires-Dist: napari[all]>=0.4.16
Requires-Dist: qtpy
Requires-Dist: magicgui
Requires-Dist: numpy
Requires-Dist: pandas
Requires-Dist: scikit-image
Requires-Dist: napari-toolkit
Requires-Dist: matplotlib
Dynamic: license-file
